{
  "file_name": "RFP_AX 기반의 차세대 업무시스템 구축을 위한 ISMP.hwpx",
  "source_path": "",
  "relative_path": "00. RAG 소스/01. RFP/RFP_AX 기반의 차세대 업무시스템 구축을 위한 ISMP.hwpx",
  "section_group": "RFP_AX 기반의 차세대 업무시스템 구축을 위한 ISMP.hwpx",
  "document_type": "hwpx",
  "total_slides": 1,
  "structure_mode": "semantic_sections",
  "sections": [
    {
      "section_id": "1",
      "section_name": "표지",
      "slide_range": [
        1,
        1
      ],
      "slide_numbers": [
        1
      ],
      "slide_label": "페이지 1",
      "keywords": [
        "표지",
        "<AX 기반의 차세대 업무시스템 구축을 위한 ISMP 제안요청서>",
        "년 2월",
        "<담당><경영기획실 정보보안관리팀><팀장 정무영><TEL",
        "-230-1831><FAX",
        "-230-1912><수석 민윤기><TEL",
        "-230-1853>",
        "<참고><>< 공정거래 준수 안내>",
        "사업기간 연장",
        "납품기일 지연 등이 발생하여 과업이 추가로 필요한 경우",
        "민원해결",
        "분쟁조정신청"
      ],
      "subsections": [
        {
          "section_id": "1.1",
          "section_name": "<AX 기반의 차세대 업무시스템 구축을 위한 ISMP 제안요청서>",
          "parent_section": "1. 표지",
          "slide_range": [
            1,
            1
          ],
          "slide_numbers": [
            1
          ],
          "slide_label": "페이지 1",
          "subsections": [],
          "content_items": [
            "<>",
            "<>",
            "2026년 2월",
            "<담당><경영기획실 정보보안관리팀><팀장 정무영><TEL:053-230-1831><FAX:053-230-1912><수석 민윤기><TEL:053-230-1853>",
            "<참고><>< 공정거래 준수 안내>",
            "< < 한국지능정보사회진흥원 공정거래 준수 안내 > 한국지능정보사회진흥원은 자율적인 거래관행 개선, 공정한 거래․상생문화를 정착‧확산하도록 공정거래 자율준수 프로그램에 따라 아래의 내용을 준수합니다. ⑴ 적정한 사업 원가를 조사‧산정하고 절차에 따라 적정한 대가를 지급합니다. ⑵ 계약업체의 책임이 없는 사유로 사업변경, 사업기간 연장, 납품기일 지연 등이 발생하여 과업이 추가로 필요한 경우, 조건 및 비용에 대하여 계약업체와 충분히 협의하여 진행하겠습니다. ⑶ 사업의 특성, 작업환경 등 제반 여건을 고려하지 않고 관리비 등 ‘간접비’의 금액이나 총 계약금액에서 간접비가 차지하는 비중을 일률적으로 제한하는 행위를 하지 않습니다. ⑷ 계약업체의 이윤을 별도 항목으로 계상하지 않고 사업비의 각 항목에 포함하는 행위를 하지 않습니다. ⑸ 한국지능정보사회진흥원이 부담해야 할 행정절차, 민원해결, 환경관리 등에 관한 책임이나 그에 소요되는 비용을 계약업체에게 부담하는 행위를 하지 않습니다. ⑹ 천재지변, 매장 문화재 발견 등 계약시점에서 계약업체가 예측할 수 없는 사항에 관한 책임이나 비용을 계약업체에게 부담하는 행위를 하지 않습니다. ⑺ 사업 수행 또는 그 준비 과정에서 계약업체가 취득한 정보 · 자료 · 물건 등의 소유 · 사용에 관한 권리를 부당하게 한국지능정보사회진흥원에게 귀속하는 행위를 하지 않습니다. ⑻ 한국지능정보사회진흥원의 손해배상 책임을 관계법령 등에 규정된 기준에 비해 과도하게 경감하거나 계약업체의 손해배상 책임, 하자담보 책임 등을 과도하게 가중하는 행위를 하지 않습니다. ⑼ 계약상 의무 위반에 대한 계약업체의 이의제기, 분쟁조정신청, 손해배상>",
            "Section 1 (Contents/section0.xml)",
            "AX 기반의 차세대 업무시스템 구축을 위한 ISMP 제안요청서 2026년 2월 담당 경영기획실 정보보안관리팀 팀장 정무영 TEL:053-230-1831 FAX:053-230-1912 수석 민윤기 TEL:053-230-1853 그림입니다."
          ],
          "keywords": [
            "<AX 기반의 차세대 업무시스템 구축을 위한 ISMP 제안요청서>",
            "년 2월",
            "<담당><경영기획실 정보보안관리팀><팀장 정무영><TEL",
            "-230-1831><FAX",
            "-230-1912><수석 민윤기><TEL",
            "-230-1853>",
            "<참고><>< 공정거래 준수 안내>",
            "사업기간 연장",
            "납품기일 지연 등이 발생하여 과업이 추가로 필요한 경우",
            "민원해결",
            "분쟁조정신청",
            "손해배상>"
          ],
          "page_type": "cover"
        }
      ]
    }
  ],
  "cover_page": {
    "title": "<AX 기반의 차세대 업무시스템 구축을 위한 ISMP 제안요청서>",
    "organization": "제안요청",
    "project_name": "",
    "date": "2026년 2월",
    "document_type": "제안요청서",
    "keywords": [
      "AX",
      "기반의",
      "차세대",
      "업무시스템",
      "구축을",
      "위한",
      "ISMP",
      "제안요청서"
    ],
    "confidence": 0.8
  },
  "toc": {
    "sections": [
      {
        "level": 1,
        "title": "xml) ---",
        "page": null
      },
      {
        "level": 2,
        "title": "원본 그림의 이름: 한국지능정보사회진흥원_국_가로",
        "page": null
      },
      {
        "level": 2,
        "title": "⑴ 적정한 사업 원가를 조사‧산정하고 절차에 따라 적정한 대가를 지급합니다",
        "page": null
      },
      {
        "level": 2,
        "title": "⑶ 사업의 특성, 작업환경 등 제반 여건을 고려하지 않고 관리비 등 ‘간접비’의 금액이나",
        "page": null
      },
      {
        "level": 2,
        "title": "⑷ 계약업체의 이윤을 별도 항목으로 계상하지 않고 사업비의 각 항목에 포함하는 행위를 하지",
        "page": null
      },
      {
        "level": 2,
        "title": "⑸ 한국지능정보사회진흥원이 부담해야 할 행정절차, 민원해결, 환경관리 등에 관한 책임이나",
        "page": null
      },
      {
        "level": 2,
        "title": "⑹ 천재지변, 매장 문화재 발견 등 계약시점에서 계약업체가 예측할 수 없는 사항에 관한 책",
        "page": null
      },
      {
        "level": 2,
        "title": "⑺ 사업 수행 또는 그 준비 과정에서 계약업체가 취득한 정보 · 자료 · 물건 등의 소유",
        "page": null
      },
      {
        "level": 2,
        "title": "⑻ 한국지능정보사회진흥원의 손해배상 책임을 관계법령 등에 규정된 기준에 비해 과도하게 경감",
        "page": null
      },
      {
        "level": 2,
        "title": "⑼ 계약상 의무 위반에 대한 계약업체의 이의제기, 분쟁조정신청, 손해배상청구 등을 제한하거",
        "page": null
      },
      {
        "level": 2,
        "title": "⑽ 계약해제 · 해지사유 등을 정함에 있어 한국지능정보사회진흥원에 대해서는 민법, 국가계약",
        "page": null
      },
      {
        "level": 2,
        "title": "⑾ 계약업체가 계약상 의무의 이행을 지체한 경우 국가계약·지방계약법령 등에서 정한 수준 이",
        "page": null
      },
      {
        "level": 2,
        "title": "⑿ 계약업체에게 제공하기로 한 장비, 시설 등의 인도가 지연되거나, 그 수량이 부족한 경우",
        "page": null
      },
      {
        "level": 2,
        "title": "- 또는, 계약업체에게 제공한 장비, 시설 등이 계약업체의 책임 없는 사유로 멸실, 훼손된",
        "page": null
      },
      {
        "level": 2,
        "title": "⒀ 사업 수행 시 적정 사업 수행 기간을 확보하여 사업을 추진합니다",
        "page": null
      },
      {
        "level": 2,
        "title": "⒂ 법령에 위반되지 않는 범위 내에서 원칙적으로 공동도급을 통한 사업 수행을 권장합니다",
        "page": null
      },
      {
        "level": 2,
        "title": "< 하도급법에 규정된 불공정행위 유형 > ‣ 하도급업체에 대한 ▲계약서 교부의무, ▲법정기",
        "page": null
      },
      {
        "level": 2,
        "title": "⒅ 한국지능정보사회진흥원은 사업 수행과정에서 느끼는 애로·불만사항을 제보할 수 있도록 온라",
        "page": null
      },
      {
        "level": 2,
        "title": "< 한국지능정보사회진흥원 애로사항 등 익명제보시스템 (레드휘슬) 안내 > 1",
        "page": null
      },
      {
        "level": 1,
        "title": "신고요령 : 직접방문, 우편, 이메일(감사실장), 신고사이트 방문( 0 http\\://ww",
        "page": null
      },
      {
        "level": 1,
        "title": "신고 시 유의사항 : 신고자 및 신고내용은 비공개로 처리되나, 제보자의 인적사항(성명, 연",
        "page": null
      },
      {
        "level": 2,
        "title": "특히 제안서 접수, 제안업체 평가 등 평가체계 전반을 온라인화 하고, 제안서 평가 전 과정",
        "page": null
      },
      {
        "level": 2,
        "title": "또한 사업관리 전반에 온라인 영상 회의 시스템을 적극",
        "page": null
      }
    ],
    "section_titles": [
      "xml) ---",
      "원본 그림의 이름: 한국지능정보사회진흥원_국_가로",
      "⑴ 적정한 사업 원가를 조사‧산정하고 절차에 따라 적정한 대가를 지급합니다",
      "⑶ 사업의 특성, 작업환경 등 제반 여건을 고려하지 않고 관리비 등 ‘간접비’의 금액이나",
      "⑷ 계약업체의 이윤을 별도 항목으로 계상하지 않고 사업비의 각 항목에 포함하는 행위를 하지",
      "⑸ 한국지능정보사회진흥원이 부담해야 할 행정절차, 민원해결, 환경관리 등에 관한 책임이나",
      "⑹ 천재지변, 매장 문화재 발견 등 계약시점에서 계약업체가 예측할 수 없는 사항에 관한 책",
      "⑺ 사업 수행 또는 그 준비 과정에서 계약업체가 취득한 정보 · 자료 · 물건 등의 소유",
      "⑻ 한국지능정보사회진흥원의 손해배상 책임을 관계법령 등에 규정된 기준에 비해 과도하게 경감",
      "⑼ 계약상 의무 위반에 대한 계약업체의 이의제기, 분쟁조정신청, 손해배상청구 등을 제한하거",
      "⑽ 계약해제 · 해지사유 등을 정함에 있어 한국지능정보사회진흥원에 대해서는 민법, 국가계약",
      "⑾ 계약업체가 계약상 의무의 이행을 지체한 경우 국가계약·지방계약법령 등에서 정한 수준 이",
      "⑿ 계약업체에게 제공하기로 한 장비, 시설 등의 인도가 지연되거나, 그 수량이 부족한 경우",
      "- 또는, 계약업체에게 제공한 장비, 시설 등이 계약업체의 책임 없는 사유로 멸실, 훼손된",
      "⒀ 사업 수행 시 적정 사업 수행 기간을 확보하여 사업을 추진합니다",
      "⒂ 법령에 위반되지 않는 범위 내에서 원칙적으로 공동도급을 통한 사업 수행을 권장합니다",
      "< 하도급법에 규정된 불공정행위 유형 > ‣ 하도급업체에 대한 ▲계약서 교부의무, ▲법정기",
      "⒅ 한국지능정보사회진흥원은 사업 수행과정에서 느끼는 애로·불만사항을 제보할 수 있도록 온라",
      "< 한국지능정보사회진흥원 애로사항 등 익명제보시스템 (레드휘슬) 안내 > 1",
      "신고요령 : 직접방문, 우편, 이메일(감사실장), 신고사이트 방문( 0 http\\://ww",
      "신고 시 유의사항 : 신고자 및 신고내용은 비공개로 처리되나, 제보자의 인적사항(성명, 연",
      "특히 제안서 접수, 제안업체 평가 등 평가체계 전반을 온라인화 하고, 제안서 평가 전 과정",
      "또한 사업관리 전반에 온라인 영상 회의 시스템을 적극"
    ],
    "keywords": [
      "가로",
      "대한",
      "이행을",
      "사항에",
      "문화재",
      "제보자의",
      "http",
      "등에서",
      "전반에",
      "준비",
      "원본",
      "이윤을",
      "환경관리",
      "기준에",
      "제안업체",
      "권장합니다",
      "확보하여",
      "항목에",
      "의무",
      "계약업체가"
    ],
    "confidence": 1.0
  },
  "detected_sections": [
    "xml) ---",
    "원본 그림의 이름: 한국지능정보사회진흥원_국_가로",
    "⑴ 적정한 사업 원가를 조사‧산정하고 절차에 따라 적정한 대가를 지급합니다",
    "⑶ 사업의 특성, 작업환경 등 제반 여건을 고려하지 않고 관리비 등 ‘간접비’의 금액이나",
    "⑷ 계약업체의 이윤을 별도 항목으로 계상하지 않고 사업비의 각 항목에 포함하는 행위를 하지",
    "⑸ 한국지능정보사회진흥원이 부담해야 할 행정절차, 민원해결, 환경관리 등에 관한 책임이나",
    "⑹ 천재지변, 매장 문화재 발견 등 계약시점에서 계약업체가 예측할 수 없는 사항에 관한 책",
    "⑺ 사업 수행 또는 그 준비 과정에서 계약업체가 취득한 정보 · 자료 · 물건 등의 소유",
    "⑻ 한국지능정보사회진흥원의 손해배상 책임을 관계법령 등에 규정된 기준에 비해 과도하게 경감",
    "⑼ 계약상 의무 위반에 대한 계약업체의 이의제기, 분쟁조정신청, 손해배상청구 등을 제한하거",
    "⑽ 계약해제 · 해지사유 등을 정함에 있어 한국지능정보사회진흥원에 대해서는 민법, 국가계약",
    "⑾ 계약업체가 계약상 의무의 이행을 지체한 경우 국가계약·지방계약법령 등에서 정한 수준 이",
    "⑿ 계약업체에게 제공하기로 한 장비, 시설 등의 인도가 지연되거나, 그 수량이 부족한 경우",
    "- 또는, 계약업체에게 제공한 장비, 시설 등이 계약업체의 책임 없는 사유로 멸실, 훼손된",
    "⒀ 사업 수행 시 적정 사업 수행 기간을 확보하여 사업을 추진합니다",
    "⒂ 법령에 위반되지 않는 범위 내에서 원칙적으로 공동도급을 통한 사업 수행을 권장합니다",
    "< 하도급법에 규정된 불공정행위 유형 > ‣ 하도급업체에 대한 ▲계약서 교부의무, ▲법정기",
    "⒅ 한국지능정보사회진흥원은 사업 수행과정에서 느끼는 애로·불만사항을 제보할 수 있도록 온라",
    "< 한국지능정보사회진흥원 애로사항 등 익명제보시스템 (레드휘슬) 안내 > 1",
    "신고요령 : 직접방문, 우편, 이메일(감사실장), 신고사이트 방문( 0 http\\://ww"
  ],
  "document_summary": "<AX 기반의 차세대 업무시스템 구축을 위한 ISMP 제안요청서> | <> <AX 기반의 차세대 업무시스템 구축을 위한 ISMP 제안요청서> <>  2026년 2월  <담당><경영기획실 정보보안관리팀><팀장 정무영><TEL:053-230-1831><FAX:053-230-1912><수석 민윤기><TEL:053-230-1853>  <참고><>< 공정거래 준수 안내> < < 한국지능정보사회진흥원 공정거래 준수 안내 > 한국지능정보",
  "page_types": [
    "cover"
  ],
  "semantic_tags": {
    "methodology": "",
    "domain": "",
    "technology": ""
  }
}