{
  "file_name": "RFP_전화시스템 고도화를 위한 ISP 사업.hwp",
  "source_path": "",
  "relative_path": "00. RAG 소스/01. RFP/RFP_전화시스템 고도화를 위한 ISP 사업.hwp",
  "section_group": "RFP_전화시스템 고도화를 위한 ISP 사업.hwp",
  "document_type": "hwp",
  "total_slides": 1,
  "structure_mode": "semantic_sections",
  "sections": [
    {
      "section_id": "1",
      "section_name": "표지",
      "slide_range": [
        1,
        1
      ],
      "slide_numbers": [
        1
      ],
      "slide_label": "페이지 1",
      "keywords": [
        "표지",
        "<그림>",
        "제 안 요 청 서",
        "<표>",
        ". 2.",
        ". 배경"
      ],
      "subsections": [
        {
          "section_id": "1.1",
          "section_name": "<그림>",
          "parent_section": "1. 표지",
          "slide_range": [
            1,
            1
          ],
          "slide_numbers": [
            1
          ],
          "slide_label": "페이지 1",
          "subsections": [],
          "content_items": [
            "제 안 요 청 서",
            "<표>",
            "2022. 2.",
            "<표>",
            "<표>",
            "<표>",
            "<표>",
            "1. 배경"
          ],
          "keywords": [
            "<그림>",
            "제 안 요 청 서",
            "<표>",
            ". 2.",
            ". 배경"
          ],
          "page_type": "cover"
        }
      ]
    }
  ],
  "cover_page": {
    "title": "<그림>",
    "organization": "계약체결일로부",
    "project_name": "",
    "date": "2022년 2월",
    "document_type": "제안서",
    "keywords": [
      "그림"
    ],
    "confidence": 0.8
  },
  "toc": {
    "sections": [
      {
        "level": 1,
        "title": "기준)",
        "page": null
      },
      {
        "level": 1,
        "title": "전화시스템 구성도(IPT/UC 및 고객센터)",
        "page": null
      },
      {
        "level": 1,
        "title": "추진목표",
        "page": null
      },
      {
        "level": 1,
        "title": "추진방향",
        "page": null
      },
      {
        "level": 1,
        "title": "추진체계",
        "page": null
      },
      {
        "level": 1,
        "title": "추진일정",
        "page": null
      },
      {
        "level": 1,
        "title": "사업추진내용",
        "page": null
      },
      {
        "level": 1,
        "title": "5) 교체 및 신규 클라우드·가상화 시스템 도입에 따른 안정적 운영방안 제시",
        "page": null
      },
      {
        "level": 1,
        "title": ")에 따라, 공공부문 클라우드 전면 전환(~’25년)",
        "page": null
      },
      {
        "level": 1,
        "title": "요구사항 개요",
        "page": null
      },
      {
        "level": 2,
        "title": "제안업체는 제안요청서에 기술된 요구사항을 기반으로 제안하되 업무분석단계에서 보다 창의적인",
        "page": null
      }
    ],
    "section_titles": [
      "기준)",
      "전화시스템 구성도(IPT/UC 및 고객센터)",
      "추진목표",
      "추진방향",
      "추진체계",
      "추진일정",
      "사업추진내용",
      "5) 교체 및 신규 클라우드·가상화 시스템 도입에 따른 안정적 운영방안 제시",
      ")에 따라, 공공부문 클라우드 전면 전환(~’25년)",
      "요구사항 개요",
      "제안업체는 제안요청서에 기술된 요구사항을 기반으로 제안하되 업무분석단계에서 보다 창의적인"
    ],
    "keywords": [
      "기준",
      "제안요청서에",
      "공공부문",
      "요구사항",
      "업무분석단계에서",
      "창의적인",
      "개요",
      "사업추진내용",
      "따른",
      "안정적",
      "운영방안",
      "전환",
      "보다",
      "추진체계",
      "제안업체는",
      "신규",
      "시스템",
      "제시",
      "요구사항을",
      "전면"
    ],
    "confidence": 1.0
  },
  "detected_sections": [
    "기준)",
    "전화시스템 구성도(IPT/UC 및 고객센터)",
    "추진목표",
    "추진방향",
    "추진체계",
    "추진일정",
    "사업추진내용",
    "5) 교체 및 신규 클라우드·가상화 시스템 도입에 따른 안정적 운영방안 제시",
    ")에 따라, 공공부문 클라우드 전면 전환(~’25년)",
    "요구사항 개요",
    "제안업체는 제안요청서에 기술된 요구사항을 기반으로 제안하되 업무분석단계에서 보다 창의적인",
    "제안요청서",
    "사업개요",
    "사업내용",
    "사업범위",
    "사업기간",
    "기대효과",
    "선진사례",
    "세부일정",
    "이행계획 수립"
  ],
  "document_summary": "<그림> | <그림>    제 안 요 청 서  <표>  2022. 2.  <그림>  <표>  <표>  <표>  <표>   1. 배경  <표>   ❍ 노후화된 전화시스템 장비의 교체시기가 도래함에 따라 효율적인 교체 방안 마련과 더불어, 향후 공단 환경에 적합한 전화시스템 재구축을 위한 종합적인 정보화전략 컨설팅 추진   2. 사업개요  ❍ 사 업 명:「전화시스템 고도화",
  "page_types": [
    "cover"
  ],
  "semantic_tags": {
    "methodology": "",
    "domain": "",
    "technology": ""
  }
}